invenio_files_rest/__init__.py
invenio_files_rest/admin.py
invenio_files_rest/app.py
invenio_files_rest/cli.py
invenio_files_rest/config.py
invenio_files_rest/errors.py
invenio_files_rest/ext.py
invenio_files_rest/formparser.py
invenio_files_rest/helpers.py
invenio_files_rest/limiters.py
invenio_files_rest/models.py
invenio_files_rest/permissions.py
invenio_files_rest/proxies.py
invenio_files_rest/serializer.py
invenio_files_rest/signals.py
invenio_files_rest/tasks.py
invenio_files_rest/utils.py
invenio_files_rest/views.py
invenio_files_rest/wrappers.py
invenio_files_rest/alembic/08e4a71525b6_change_datetime_types.py
invenio_files_rest/alembic/2e97565eba72_create_files_rest_tables.py
invenio_files_rest/alembic/52ce868f33c3_create_files_rest_branch.py
invenio_files_rest/alembic/8ae99b034410_create_files_objecttags_table.py
invenio_files_rest/alembic/a29271fd78f8_create_files_object_partial_unique_index.py
invenio_files_rest/alembic/e172c837b036_add_indexes.py
invenio_files_rest/alembic/f741aa746a7d_alter_files_files_last_check_column_to_.py
invenio_files_rest/storage/__init__.py
invenio_files_rest/storage/base.py
invenio_files_rest/storage/pyfs.py
invenio_files_rest/translations/messages.pot
invenio_files_rest/translations/ar/LC_MESSAGES/messages.mo
invenio_files_rest/translations/ar/LC_MESSAGES/messages.po
invenio_files_rest/translations/bg/LC_MESSAGES/messages.mo
invenio_files_rest/translations/bg/LC_MESSAGES/messages.po
invenio_files_rest/translations/ca/LC_MESSAGES/messages.mo
invenio_files_rest/translations/ca/LC_MESSAGES/messages.po
invenio_files_rest/translations/cs/LC_MESSAGES/messages.mo
invenio_files_rest/translations/cs/LC_MESSAGES/messages.po
invenio_files_rest/translations/da/LC_MESSAGES/messages.mo
invenio_files_rest/translations/da/LC_MESSAGES/messages.po
invenio_files_rest/translations/de/LC_MESSAGES/messages.mo
invenio_files_rest/translations/de/LC_MESSAGES/messages.po
invenio_files_rest/translations/el/LC_MESSAGES/messages.mo
invenio_files_rest-4.0.0.dist-info/licenses/AUTHORS.rst
invenio_files_rest-4.0.0.dist-info/licenses/LICENSE
invenio_files_rest-4.0.0.dist-info/METADATA
invenio_files_rest-4.0.0.dist-info/WHEEL
invenio_files_rest-4.0.0.dist-info/entry_points.txt
invenio_files_rest-4.0.0.dist-info/top_level.txt
invenio_files_rest-4.0.0.dist-info/RECORD
