Metadata-Version: 2.4
Name: invenio-files-rest
Version: 4.0.0
Summary: "Files download/upload REST API similar to S3 for Invenio."
Home-page: https://github.com/inveniosoftware/invenio-files-rest
Author: CERN
Author-email: info@inveniosoftware.org
License: MIT
Keywords: invenio files REST
Platform: any
Classifier: Development Status :: 5 - Production/Stable
Requires-Python: >=3.7
License-File: LICENSE
License-File: AUTHORS.rst
Requires-Dist: click-default-group<2.0.0,>=1.2.2
Requires-Dist: Flask-WTF>=0.15.1
Requires-Dist: invenio-accounts<8.0.0,>=7.0.0
Requires-Dist: invenio-i18n<4.0.0,>=3.0.0
Requires-Dist: marshmallow-utils>=0.14.1
Provides-Extra: tests
Requires-Dist: pytest-black>=0.6.0; extra == "tests"
Requires-Dist: future>=0.18.2; extra == "tests"
Requires-Dist: invenio-access<6.0.0,>=5.0.0; extra == "tests"
Requires-Dist: invenio-admin<2.0.0,>=1.6.0; extra == "tests"
Requires-Dist: invenio-db[mysql,postgresql,versioning]<3.0.0,>=2.2.0; extra == "tests"
Requires-Dist: pytest-invenio<5.0.0,>=4.0.0; extra == "tests"
Requires-Dist: sphinx<6.0.0,>=5.0.0; extra == "tests"
Requires-Dist: standard-imghdr<4.0.0,>=3.13.0; python_version >= "3.13" and extra == "tests"
Requires-Dist: sphinxcontrib-httpdomain>=1.4.0; extra == "tests"
Provides-Extra: postgresql
Provides-Extra: mysql
Provides-Extra: sqlite
Dynamic: license-file
